matyimodule/__init__.py
matyimodule/app.py
matyimodule/matyimodule.py
matyimodule-1.0.dist-info/METADATA
matyimodule-1.0.dist-info/WHEEL
matyimodule-1.0.dist-info/entry_points.txt
matyimodule-1.0.dist-info/top_level.txt
matyimodule-1.0.dist-info/RECORD
